FYP_crawler/__init__.py
FYP_crawler/tweet_crawler.py
FYP_crawler-0.0.1.dist-info/METADATA
FYP_crawler-0.0.1.dist-info/WHEEL
FYP_crawler-0.0.1.dist-info/license.txt
FYP_crawler-0.0.1.dist-info/top_level.txt
FYP_crawler-0.0.1.dist-info/RECORD
