Metadata-Version: 2.1
Name: FYP-crawler
Version: 0.0.1
Home-page: https://gitee.com/li-muquan/slgs1
Author: slgs
Classifier: Programming Language :: Python :: 3
Classifier: License :: OSI Approved :: MIT License
Classifier: Operating System :: OS Independent
License-File: license.txt
